generest/__init__.py
generest/cli/__init__.py
generest/cli/main.py
generest-4.dist-info/LICENSE
generest-4.dist-info/METADATA
generest-4.dist-info/WHEEL
generest-4.dist-info/entry_points.txt
generest-4.dist-info/top_level.txt
generest-4.dist-info/RECORD
