Metadata-Version: 2.1
Name: generest
Version: 4
Home-page: https://gitlab.com/sol-courtney/python-packages/generest
Download-URL: https://gitlab.com/sol-courtney/python-packages/generest
Author: Sol Courtney
Author-email: sol.courtney@gmail.com
Maintainer: Sol Courtney
Maintainer-email: sol.courtney@gmail.com
License: GNU General Public License v3 (GPLv3)
Project-URL: Documentation, https://generest.readthedocs.io
Project-URL: Gitlab Pages, https://sol-courtney.gitlab.io/python-packages/generest
Project-URL: Source Code, https://gitlab.com/sol-courtney/python-packages/generest
Project-URL: Tracker, https://gitlab.com/sol-courtney/python-packages/generest/-/issues
Keywords: Gitlab,Python
Classifier: Intended Audience :: Developers
Classifier: Intended Audience :: Information Technology
Classifier: License :: OSI Approved :: GNU General Public License v3 (GPLv3)
Classifier: Operating System :: OS Independent
Classifier: Programming Language :: Python
Classifier: Programming Language :: Python :: 3
Classifier: Programming Language :: Python :: 3.11
Requires-Python: >=3.9
License-File: LICENSE
Requires-Dist: click
